{
    "/newPageDefs2/auth_media_producer": {
        "menu_system": "._12-z",
        "admin_panel": "//html/body/div[3]/div/div/div/div/div/div[2]/span/div/div/div[2]",
        "manage_roles": "//html/body/div[4]/div/div/div/div/div/div[10]/span/div/div/div/span",
        "enter_email_address": "#__manageRoles_emailInput",
        "choose_role": "._1ogr",
        "role_window": "._3y07",
        "grant_role": "//html/body/div[3]/div/div/div[2]/button[1]/div/span",
        "revoke_role": "//html/body/div[3]/div/div/div[2]/button[2]/div/span",
        "create_course": "//*[@id='container']/div/div[2]/div/div/div/div/div[3]/div/button/div/div/span",
        "course_name": "#__createCourse_nameInput",
        "course_code": "#__createCourse_codeInput",
        "learning_Objective": "._2oIm _2lfL _2Kdo _3vV4 ",
        "save_button": "._1tkc undefined",
        "isbn_number": "#__createCourse_isbnInput",
        "resources_button": "#react-tabs-20",
        "add_folder": "._1tkc _1C6k",
        "folder_name": "#0757b5da-e0a6-48e3-becd-ad4fc96c4bea",
        "course_validation": "#//*[@id='container']/div/div[2]/div[1]/div/div/div[3]/div/div/a",
        "card_name": ".DOD8 CourseCard_draft CourseCard_product_1 CourseCard_template",
        "resources_tab": "//*[text()= 'RESOURCES']",
        "Add_button": "//*[@id='container']/div/div/div/div[5]/button/div/div",
        "ActivitySearchInput": "//*[@id='__ActivitySearchInput']",
        "Adding_chapter_content": "._2UlN _18eG",
        "add_folder_button": "//html/body/div[2]/div/div/div[3]/div[2]/button",
        "options_button": "//html/body/div/div/div/div/div[4]/div/div/div/div[2]/div[2]/div[1]/div/div/div[3]/div/button",
        "OpenFolder": "//html/body/div[2]/div/div/div[2]/div[1]/div/div/div/div[2]/div[1]/div/div/div[1]/button",
        "OpenFolder1": "//html/body/div[2]/div/div/div[2]/div/div/div/div/div[2]/div[2]/div/div/div[1]/button",
        "move_item_button": "//html/body/div[2]/div/div/div/div/div/div[2]/span/div/div/div/span",
        "chapter_2": "//html/body/div[2]/div/div/div[2]/div/div/div/div/div[2]/div[5]/div/div/div[2]/button/span",
        "place_item_button": "//html/body/div[2]/div/div/div[3]/div[2]/button",
        "chapter_1_3": "//html/body/div[2]/div/div/div[2]/div/div/div/div/div[2]/div[4]/div/div/div[2]/button",
        "chapter_1_4": "//html/body/div[2]/div/div/div[2]/div/div/div/div/div[2]/div[3]/div/div/div[2]/button",
        "reorder_button": "//html/body/div[2]/div/div/div/div/div/div[3]/span/div/div/div",
        "move_down_button": "//html/body/div[2]/div/div/div[2]/div/div[2]/button[3]",
        "save_reordered_button": "//html/body/div[2]/div/div/div[3]/div[2]/button",
        "open_menu": "._1plU _1j68",
        "edit_button": "//html/body/div[3]/div/div/div/div/div/div[1]/span/div/div/div/span",
        "Template_status": "._2oIm _1bTe ",
        "Active_Date": "._52qp",
        "course_end": ".//*[@class='_52qp']",
        "Template_validate": "//*[text()='Template']",
        "chapter1-1": "//html/body/div[2]/div/div/div[2]/div/div/div/div/div[2]/div[1]/div[2]/div[1]/div/div/div[2]/button/span",
        "chapter1-2": "//html/body/div[2]/div/div/div[2]/div/div/div/div/div[2]/div[1]/div[2]/div[2]/div/div/div[2]/button",
        "chapter1-(3)": "//html/body/div[2]/div/div/div[2]/div/div/div/div/div[2]/div[1]/div[2]/div[3]/div/div/div[2]/button",
        "chapter2-1": "//html/body/div[2]/div/div/div[2]/div/div/div/div/div[2]/div[2]/div[2]/div/div/div/div[2]/button",
        "OpenActionMenuForChapter1": "(//*[@class='_3xl4'])[3]",
        "OpenActionMenuForChapter2": "(//*[@class='_3xl4'])[4]",
        "OpenActionMenuForChapter3": "(//*[@class='_3xl4'])[5]",
        "OpenActionMenuForChapter4": "(//*[@class='_3xl4'])[6]",
        "file_open": "//*[@class='_3BbM']",
        "Plus_button": "//*[@id='container']/div/div[2]/div[2]/button/div/div",
        "course_card_2": ".DOD8 CourseCard_draft CourseCard_product_2 CourseCard_template",
        "Resource_tab_writing": "//*[@id='react-tabs-24']/span",
        "folder_name_writing": "//*[@class='_3dMU _1EX4 ']",
        "edit_button_writing": "(//*[@class='_1plU _1j68'])[2]",
        "chapter_2_InstructorReview_writing": "//html/body/div[2]/div/div/div[2]/div/div/div/div/div[2]/div[1]/div/div/div[2]",
        "placefolder_writing": "//html/body/div[2]/div/div/div[2]/div[1]/div/div/div/div[2]/div[3]/div/div/div[2]/button",
        "chapter1_peerReview": "//html/body/div[2]/div/div/div[2]/div/div/div/div/div[2]/div[2]/div/div/div[2]/button/span"
    }
}