{
  "create_course": {
    "create_course_success": "Created.",
    "course_copied": "Course Copied",
    "edit_course_sucess": "Read & Practice Template Updated.",
    "updated" : "Updated.",
    "email_notification": "invites",
    "enrollement": "Enrolled macmillanstudent5@gmail.com.",
    "create_course_skills_success": "Skills Template Created.",
    "create_course_reading_success": "Read & Practice Template Created.",
    "create_course_reading_media_sucess": "Read & Practice Course Created",
    "course_activation" : "COPY OF Edit TestcourseRead & Practice course Updated.",
    "check_email_message" : "Check your email",
    "admin_message" : "Admin privileges have been granted for buvaciw@simpleemail.info.\nClose",
    "customer_support_message" : "Customer Support privileges have been granted for mediaeditor13@gmail.com.\nClose",
    "medai_producer_message": "Media Producer privileges have been granted for dusum@businessagent.email.\nClose",
    "paid_access_message":"Paid Access Code Creator privileges have been granted for paidaccess09@gmail.com.\nClose",
    "edit_course_message_skills": "Skills Template Updated.",
    "edit_course_message_reading": "Read & Practice Template Updated.",
    "create_course_Qualitative_success":"Qualitative Template Created.",
    "create_course_Qual_media": "Qualitative Template TC Created.",
    "create_course_Quant_media": "Quantitative Template TC Created.",
    "url_message": "URL Link Added to Your Content."
  },
  "home": {
    "password_reset_triggered": "triggered!.",
    "manage_roles_success": "Customer Support privileges have been granted for student4@courseware.com",
    "manage_roles_revoke": "Customer Support privileges have been revoked for student4@courseware.com"
  },
  "update_access_code" : {
    "success_message": "Code update successful.."
  },
  "course_page": {
    "update_course_success": "have been updated.",
    "assigned_course_success": "has been assigned."
    
  }
}
